manuf2/__init__.py
manuf2/__main__.py
manuf2/manuf
manuf2/manuf.py
manuf2-2.0.2.dist-info/licenses/LICENSE.txt
manuf2-2.0.2.dist-info/METADATA
manuf2-2.0.2.dist-info/WHEEL
manuf2-2.0.2.dist-info/entry_points.txt
manuf2-2.0.2.dist-info/top_level.txt
manuf2-2.0.2.dist-info/RECORD
