Metadata-Version: 2.4
Name: manuf2
Version: 2.0.2
Summary: Parser library for Wireshark's OUI database
Home-page: https://github.com/joshschmelzle/manuf2
Author: Josh Schmelzle, Michael Huang
License: Apache License 2.0 or GPLv3
Keywords: manuf2,mac address,networking
License-File: LICENSE.txt
Requires-Dist: requests
Requires-Dist: certifi
Dynamic: author
Dynamic: description
Dynamic: description-content-type
Dynamic: home-page
Dynamic: keywords
Dynamic: license
Dynamic: license-file
Dynamic: requires-dist
Dynamic: summary
